{
  "users": [
    {
      "userAddress": {
        "country": "fffff",
        "city": "a",
        "zipCode": "d",
        "streetName": "b",
        "streetNumber": "c"
      },
      "accountType": 2,
      "accountID": 1,
      "firstName": "adasd",
      "lastName": "asdad",
      "email": "asd@gmail.com",
      "password": "asd",
      "companyContactperson": null,
      "companyPhoneNumber": null,
      "companyName": null,
      "birthDate": "asd",
      "newsLetter": 1,
      "phoneNumber": "1234123"
    }
  ]
}